ascii_colors/__init__.py
ascii_colors-0.11.5.dist-info/licenses/LICENSE
ascii_colors-0.11.5.dist-info/METADATA
ascii_colors-0.11.5.dist-info/WHEEL
ascii_colors-0.11.5.dist-info/top_level.txt
ascii_colors-0.11.5.dist-info/RECORD
