Metadata-Version: 2.4
Name: ascii_colors
Version: 0.11.5
Summary: A Python library for rich terminal output with advanced logging features.
Author-email: ParisNeo <parisneo_ai@gmail.com>
License-Expression: Apache-2.0
Project-URL: Homepage, https://github.com/ParisNeo/ascii_colors
Project-URL: Repository, https://github.com/ParisNeo/ascii_colors
Project-URL: Issues, https://github.com/ParisNeo/ascii_colors/issues
Project-URL: Documentation, https://parisneo.github.io/ascii_colors/
Keywords: ansi,color,colors,style,terminal,console,cli,rich text,logging,logger,log,structured logging,log formatting,json logging,file logging,log rotation,python logging,context logging,progress bar,progress,tqdm,indicator,menu,cli menu,interactive menu,terminal menu,navigation,prompt,confirm,input,user interaction,animation,spinner,utility
Classifier: Development Status :: 5 - Production/Stable
Classifier: Intended Audience :: Developers
Classifier: Environment :: Console
Classifier: Operating System :: OS Independent
Classifier: Programming Language :: Python :: 3
Classifier: Programming Language :: Python :: 3.8
Classifier: Programming Language :: Python :: 3.9
Classifier: Programming Language :: Python :: 3.10
Classifier: Programming Language :: Python :: 3.11
Classifier: Programming Language :: Python :: 3.12
Classifier: Topic :: System :: Logging
Classifier: Topic :: Terminals
Classifier: Topic :: Utilities
Classifier: Topic :: Software Development :: Libraries :: Python Modules
Classifier: Topic :: System :: Shells
Requires-Python: >=3.8
License-File: LICENSE
Requires-Dist: wcwidth
Provides-Extra: dev
Requires-Dist: sphinx>=4.0; extra == "dev"
Requires-Dist: sphinx-rtd-theme; extra == "dev"
Requires-Dist: sphinx-autodoc-typehints; extra == "dev"
Requires-Dist: sphinx-autobuild; extra == "dev"
Requires-Dist: sphinx_copybutton; extra == "dev"
Requires-Dist: furo; extra == "dev"
Requires-Dist: myst-parser; extra == "dev"
Requires-Dist: toml; extra == "dev"
Requires-Dist: flake8; extra == "dev"
Requires-Dist: mypy; extra == "dev"
Requires-Dist: black; extra == "dev"
Requires-Dist: isort; extra == "dev"
Dynamic: license-file
